[
	{
		"inputs": [],
		"name": "isComplete",
		"outputs": [
			{
				"internalType": "bool",
				"name": "",
				"type": "bool"
			}
		],
		"stateMutability": "view",
		"type": "function"
	},
	{
		"inputs": [
			{
				"internalType": "bytes32",
				"name": "hash",
				"type": "bytes32"
			}
		],
		"name": "lockInGuess",
		"outputs": [],
		"stateMutability": "payable",
		"type": "function"
	},
	{
		"inputs": [],
		"name": "settle",
		"outputs": [],
		"stateMutability": "nonpayable",
		"type": "function"
	}
]